knee/__init__.py
knee/clustering.py
knee/convex_hull.py
knee/curvature.py
knee/dfdt.py
knee/evaluation.py
knee/knee_ranking.py
knee/kneedle.py
knee/linear_fit.py
knee/lmethod.py
knee/menger.py
knee/metrics.py
knee/multi_knee.py
knee/postprocessing.py
knee/rdp.py
knee/zmethod.py
knee-0.1.1.dist-info/LICENSE
knee-0.1.1.dist-info/METADATA
knee-0.1.1.dist-info/WHEEL
knee-0.1.1.dist-info/top_level.txt
knee-0.1.1.dist-info/RECORD
