Metadata-Version: 2.1
Name: knee
Version: 0.1.1
Summary: (Multi)Knee/Elbow point detection library
Home-page: https://github.com/mariolpantunes/knee
Author: Mário Antunes
Author-email: mario.antunes@ua.pt
Classifier: Programming Language :: Python :: 3
Classifier: License :: OSI Approved :: MIT License
Classifier: Operating System :: OS Independent
Requires-Python: >=3.8
License-File: LICENSE
Requires-Dist: numpy >=1.23
Requires-Dist: pyUTSAlgorithms >=0.1.2
